pywinauto_supporter/__init__.py
pywinauto_supporter/utils.py
pywinauto_supporter-0.0.4.dist-info/METADATA
pywinauto_supporter-0.0.4.dist-info/WHEEL
pywinauto_supporter-0.0.4.dist-info/top_level.txt
pywinauto_supporter-0.0.4.dist-info/RECORD
