Metadata-Version: 2.1
Name: pywinauto-supporter
Version: 0.0.4
Summary: Pywinauto supporter
Home-page: https://github.com/automatethem/pywinauto-supporter
Author: Sang Ki Kwon
Author-email: automatethem@gmail.com
License: MIT
Requires-Dist: pywinauto
